json_flattening/__init__.py
json_flattening-1.0.5.dist-info/LICENSE
json_flattening-1.0.5.dist-info/METADATA
json_flattening-1.0.5.dist-info/WHEEL
json_flattening-1.0.5.dist-info/top_level.txt
json_flattening-1.0.5.dist-info/RECORD
