Metadata-Version: 2.1
Name: json-flattening
Version: 1.0.5
Summary: Package to Flatten JSON data to relational Dataframe
Home-page: https://github.com/rahulgoel11/json_flattening
Author: Rahul Goel
License: MIT
Keywords: json flatten
Platform: UNKNOWN
Classifier: Programming Language :: Python :: 3
Classifier: License :: OSI Approved :: MIT License
Classifier: Operating System :: OS Independent
Requires-Dist: pandas
Requires-Dist: numpy
